{
  "resourceType" : "CodeSystem",
  "id" : "jp-condition-disease-modifier-medis-record-no-cs",
  "url" : "urn:oid:1.2.392.200119.4.201.2",
  "version" : "1.2.0-dev",
  "name" : "JP_ConditionDiseaseModifierMEDISRecordNo_CS",
  "title" : "JP Core Condition Disease Modifier MEDIS Record CodeSystem",
  "status" : "active",
  "experimental" : false,
  "date" : "2023-08-05",
  "publisher" : "FHIR Japanese implementation research working group in Japan Association of Medical Informatics (JAMI)",
  "contact" : [{
    "name" : "FHIR Japanese implementation research working group in Japan Association of Medical Informatics (JAMI)",
    "telecom" : [{
      "system" : "url",
      "value" : "http://jpfhir.jp"
    },
    {
      "system" : "email",
      "value" : "office@hlfhir.jp"
    }]
  }],
  "description" : "MEDIS ICD10対応標準病名マスター(修飾語管理番号) コードシステム",
  "jurisdiction" : [{
    "coding" : [{
      "system" : "urn:iso:std:iso:3166",
      "code" : "JP",
      "display" : "Japan"
    }]
  }],
  "copyright" : "Copyright MEDIS-DC 医療情報システム開発センター",
  "caseSensitive" : true,
  "content" : "fragment",
  "concept" : [{
    "code" : "27000267",
    "display" : "過敏性"
  },
  {
    "code" : "27000027",
    "display" : "の初期"
  },
  {
    "code" : "27001344",
    "display" : "疾患"
  }]
}